toucan_connectors/__init__.py
toucan_connectors/auth.py
toucan_connectors/common.py
toucan_connectors/condition_translator.py
toucan_connectors/connection_manager.py
toucan_connectors/default-logo.png
toucan_connectors/google_credentials.py
toucan_connectors/json_wrapper.py
toucan_connectors/pagination.py
toucan_connectors/pandas_translator.py
toucan_connectors/query_manager.py
toucan_connectors/snowflake_common.py
toucan_connectors/sql_query_helper.py
toucan_connectors/toucan_connector.py
toucan_connectors/aws/aws.png
toucan_connectors/awsathena/__init__.py
toucan_connectors/awsathena/athena.png
toucan_connectors/awsathena/awsathena_connector.py
toucan_connectors/azure_mssql/__init__.py
toucan_connectors/azure_mssql/azure_mssql_connector.py
toucan_connectors/azure_mssql/sql-azure.png
toucan_connectors/clickhouse/__init__.py
toucan_connectors/clickhouse/clickhouse.png
toucan_connectors/clickhouse/clickhouse_connector.py
toucan_connectors/databricks/databricks.png
toucan_connectors/databricks/databricks_connector.py
toucan_connectors/dataiku/__init__.py
toucan_connectors/dataiku/dataiku.png
toucan_connectors/dataiku/dataiku_connector.py
toucan_connectors/denodo/denodo.png
toucan_connectors/elasticsearch/__init__.py
toucan_connectors/elasticsearch/elasticsearch.png
toucan_connectors/elasticsearch/elasticsearch_connector.py
toucan_connectors/github/GitHub_Logo.png
toucan_connectors/github/doc.md
toucan_connectors/github/github_connector.py
toucan_connectors/github/helpers.py
toucan_connectors/google_analytics/__init__.py
toucan_connectors/google_analytics/google-analytics.png
toucan_connectors/google_analytics/google_analytics_connector.py
toucan_connectors/google_big_query/__init__.py
toucan_connectors/google_big_query/google-bigquery.png
toucan_connectors/google_big_query/google_big_query_connector.py
toucan_connectors/google_cloud_mysql/__init__.py
toucan_connectors/google_cloud_mysql/google-cloud-mysql.png
toucan_connectors-10.1.0.dist-info/METADATA
toucan_connectors-10.1.0.dist-info/WHEEL
toucan_connectors-10.1.0.dist-info/top_level.txt
toucan_connectors-10.1.0.dist-info/RECORD
