Metadata-Version: 2.4
Name: toucan-connectors
Version: 10.1.0
Summary: Toucan Toco Connectors
Author-email: Toucan Toco <dev@toucantoco.com>
License: BSD
Requires-Python: <3.14,>=3.13
Requires-Dist: cached-property<3.0.0,>=1.5.2
Requires-Dist: Jinja2<4.0.0,>=3.0.3
Requires-Dist: pydantic<3.0.0,>=2.4.2
Requires-Dist: requests<3.0.0,>=2.28.0
Provides-Extra: base
Requires-Dist: Authlib<2.0.0,>=1.3.2; extra == "base"
Requires-Dist: jq<2.0.0,>=1.2.2; extra == "base"
Requires-Dist: python-slugify>=5.0.2; extra == "base"
Requires-Dist: tenacity<10.0.0,>=8.0.1; extra == "base"
Requires-Dist: pandas>=2; extra == "base"
Provides-Extra: awsathena
Requires-Dist: awswrangler<4.0.0,>=3.3.0; extra == "awsathena"
Provides-Extra: azure-mssql
Requires-Dist: pyodbc<6,>=4; extra == "azure-mssql"
Requires-Dist: sqlalchemy<3,>=2; extra == "azure-mssql"
Provides-Extra: clickhouse
Requires-Dist: clickhouse-driver<1.0,>=0.2.3; extra == "clickhouse"
Requires-Dist: sqlalchemy<3,>=2; extra == "clickhouse"
Provides-Extra: dataiku
Requires-Dist: dataiku-api-client>=9.0.1; extra == "dataiku"
Provides-Extra: elasticsearch
Requires-Dist: elasticsearch>=9; extra == "elasticsearch"
Provides-Extra: google-analytics
Requires-Dist: google-api-python-client<3,>=2; extra == "google-analytics"
Requires-Dist: oauth2client<5.0.0,>=4.1.3; extra == "google-analytics"
Provides-Extra: github
Requires-Dist: python-graphql-client<1.0,>=0.4.3; extra == "github"
Provides-Extra: google-big-query
Requires-Dist: google-cloud-bigquery[bqstorage,pandas]<4,>=3; extra == "google-big-query"
Provides-Extra: google-cloud-mysql
Requires-Dist: PyMySQL<2.0.0,>=1.1.1; extra == "google-cloud-mysql"
Provides-Extra: google-sheets
Requires-Dist: google-api-python-client<3,>=2; extra == "google-sheets"
Requires-Dist: oauth2client<5.0.0,>=4.1.3; extra == "google-sheets"
Provides-Extra: http-api
Requires-Dist: oauthlib==3.3.1; extra == "http-api"
Requires-Dist: requests-oauthlib==2.0.0; extra == "http-api"
Requires-Dist: xmltodict<1.1,>=1; extra == "http-api"
Provides-Extra: hubspot
Requires-Dist: hubspot-api-client<13,>=7.4; extra == "hubspot"
Provides-Extra: mongo
Requires-Dist: pymongo>=3.12.0; extra == "mongo"
Provides-Extra: mssql
Requires-Dist: pyodbc<6,>=4; extra == "mssql"
Requires-Dist: sqlalchemy<3,>=2; extra == "mssql"
Provides-Extra: mysql
Requires-Dist: PyMySQL<2.0.0,>=1.1.1; extra == "mysql"
Provides-Extra: odata
Requires-Dist: oauthlib==3.3.1; extra == "odata"
Requires-Dist: requests-oauthlib==2.0.0; extra == "odata"
Requires-Dist: tctc-odata<1.0,>=0.3; extra == "odata"
Provides-Extra: odbc
Requires-Dist: pyodbc<6,>=4; extra == "odbc"
Provides-Extra: oracle-sql
Requires-Dist: cx-Oracle<9.0.0,>=8.3.0; extra == "oracle-sql"
Requires-Dist: sqlalchemy<3,>=2; extra == "oracle-sql"
Provides-Extra: redshift
Requires-Dist: lxml<6.1.0,>=4.6.5; extra == "redshift"
Requires-Dist: redshift-connector<3.0.0,>=2.0.907; extra == "redshift"
Provides-Extra: peakina
Requires-Dist: peakina>=0.11; extra == "peakina"
Provides-Extra: postgres
Requires-Dist: psycopg<4,>=3.2.9; extra == "postgres"
Requires-Dist: sqlalchemy<3,>=2; extra == "postgres"
Provides-Extra: sap-hana
Requires-Dist: pyhdb<1.0,>=0.3.4; extra == "sap-hana"
Requires-Dist: sqlalchemy<3,>=2; extra == "sap-hana"
Provides-Extra: snowflake
Requires-Dist: pyarrow; extra == "snowflake"
Requires-Dist: PyJWT<3,>=1.5.3; extra == "snowflake"
Requires-Dist: snowflake-connector-python<4.1.0,>=3.0.0; extra == "snowflake"
Provides-Extra: soap
Requires-Dist: zeep<5.0.0,>=4.1.0; extra == "soap"
Requires-Dist: lxml<6.1.0,>=4.6.5; extra == "soap"
Provides-Extra: all
Requires-Dist: Authlib<2.0.0,>=1.3.2; extra == "all"
Requires-Dist: awswrangler<4.0.0,>=3.3.0; extra == "all"
Requires-Dist: clickhouse-driver<1.0,>=0.2.3; extra == "all"
Requires-Dist: cx-Oracle<9.0.0,>=8.3.0; extra == "all"
Requires-Dist: dataiku-api-client>=9.0.1; extra == "all"
Requires-Dist: elasticsearch>=9; extra == "all"
Requires-Dist: google-api-python-client<3,>=2; extra == "all"
Requires-Dist: google-cloud-bigquery[bqstorage,pandas]<4,>=3; extra == "all"
Requires-Dist: hubspot-api-client<13,>=7.4; extra == "all"
Requires-Dist: jq<2.0.0,>=1.2.2; extra == "all"
Requires-Dist: lxml<6.1.0,>=4.6.5; extra == "all"
Requires-Dist: numpy>=2; extra == "all"
Requires-Dist: oauth2client<5.0.0,>=4.1.3; extra == "all"
Requires-Dist: oauthlib==3.3.1; extra == "all"
Requires-Dist: pandas>=2; extra == "all"
Requires-Dist: peakina>=0.11; extra == "all"
Requires-Dist: psycopg<4,>=3.2.9; extra == "all"
Requires-Dist: pyarrow; extra == "all"
Requires-Dist: pyhdb<1.0,>=0.3.4; extra == "all"
Requires-Dist: PyJWT<3,>=1.5.3; extra == "all"
Requires-Dist: pymongo>=3.12.0; extra == "all"
Requires-Dist: PyMySQL<2.0.0,>=1.1.1; extra == "all"
Requires-Dist: pyodbc<6,>=4; extra == "all"
Requires-Dist: python-graphql-client<1.0,>=0.4.3; extra == "all"
Requires-Dist: python-slugify>=5.0.2; extra == "all"
Requires-Dist: redshift-connector<3.0.0,>=2.0.907; extra == "all"
Requires-Dist: requests-oauthlib==2.0.0; extra == "all"
Requires-Dist: simplejson<4,>=3.17.6; extra == "all"
Requires-Dist: snowflake-connector-python<4.1.0,>=3.0.0; extra == "all"
Requires-Dist: sqlalchemy<3,>=2; extra == "all"
Requires-Dist: tctc-odata<1.0,>=0.3; extra == "all"
Requires-Dist: tenacity<10.0.0,>=8.0.1; extra == "all"
Requires-Dist: xmltodict<1.1,>=1; extra == "all"
Requires-Dist: zeep<5.0.0,>=4.1.0; extra == "all"
